cs/context.py
cs_context-20250528.dist-info/WHEEL
cs_context-20250528.dist-info/METADATA
cs_context-20250528.dist-info/RECORD
